my_python_test_project/__init__.py
my_python_test_project/console.py
my_python_test_project/wikipedia.py
my_python_test_project-0.1.0.dist-info/entry_points.txt
my_python_test_project-0.1.0.dist-info/WHEEL
my_python_test_project-0.1.0.dist-info/METADATA
my_python_test_project-0.1.0.dist-info/RECORD
